tabularcompare/__init__.py
tabularcompare/app.py
tabularcompare/core.py
tabularcompare/utils.py
tabularcompare-0.0.4.dist-info/LICENSE
tabularcompare-0.0.4.dist-info/METADATA
tabularcompare-0.0.4.dist-info/WHEEL
tabularcompare-0.0.4.dist-info/entry_points.txt
tabularcompare-0.0.4.dist-info/top_level.txt
tabularcompare-0.0.4.dist-info/RECORD
