Metadata-Version: 2.1
Name: tabularcompare
Version: 0.0.4
Summary: Tabular data comparison wrapper for DataComPy
Author-email: Erich Henrique <erich.hs13@gmail.com>
License: Apache-2.0
Project-URL: Homepage, https://github.com/erich-hs/tabularcompare
Project-URL: Bug Tracker, https://github.com/erich-hs/tabularcompare/issues
Keywords: Tabular,Compare,Data
Classifier: License :: OSI Approved :: Apache Software License
Classifier: Development Status :: 4 - Beta
Classifier: Programming Language :: Python :: 3.8
Classifier: Programming Language :: Python :: 3.9
Classifier: Programming Language :: Python :: 3.10
Classifier: Operating System :: OS Independent
Requires-Python: >=3.8
License-File: LICENSE
Requires-Dist: numpy (<=1.24.2,>=1.11.3)
Requires-Dist: pandas (<=1.5.3,>=0.25.0)
Requires-Dist: datacompy (<=0.9.0,>=0.8.4)
Requires-Dist: pretty-html-table (==0.9.16)
Requires-Dist: click
Requires-Dist: xlwt
Requires-Dist: xlrd
Requires-Dist: openpyxl
Provides-Extra: build
Requires-Dist: build ; extra == 'build'
Requires-Dist: twine ; extra == 'build'
Requires-Dist: wheel ; extra == 'build'
Provides-Extra: dev
Requires-Dist: pytest ; extra == 'dev'
Requires-Dist: pytest-cov ; extra == 'dev'
Requires-Dist: pylint ; extra == 'dev'
Requires-Dist: pre-commit ; extra == 'dev'
Requires-Dist: black ; extra == 'dev'
Requires-Dist: build ; extra == 'dev'
Requires-Dist: twine ; extra == 'dev'
Requires-Dist: wheel ; extra == 'dev'
Provides-Extra: qa
Requires-Dist: pylint ; extra == 'qa'
Requires-Dist: black ; extra == 'qa'
Provides-Extra: tests
Requires-Dist: pytest ; extra == 'tests'
Requires-Dist: pytest-cov ; extra == 'tests'
